has_keyword_extractor/__init__.py
has_keyword_extractor/_keyphrase_extraction.py
has_keyword_extractor/_preprocessing_text.py
has_keyword_extractor/_runner.py
has_keyword_extractor/_statistics_keywords_extraction.py
has_keyword_extractor/clean_keyphrase.py
has_keyword_extractor/cli.py
has_keyword_extractor/compute_cumulative_frequencies.py
has_keyword_extractor/compute_pooler.py
has_keyword_extractor/extract_lexicals_windows.py
has_keyword_extractor/fbi.py
has_keyword_extractor/fni.py
has_keyword_extractor/hwo.py
has_keyword_extractor/hwpo.py
has_keyword_extractor/load_camembert_model.py
has_keyword_extractor/mmr_score.py
has_keyword_extractor/ranked_ngrams.py
has_keyword_extractor/utils.py
keyword_extraction_has-0.3.0.dist-info/LICENSE
keyword_extraction_has-0.3.0.dist-info/METADATA
keyword_extraction_has-0.3.0.dist-info/WHEEL
keyword_extraction_has-0.3.0.dist-info/entry_points.txt
keyword_extraction_has-0.3.0.dist-info/top_level.txt
keyword_extraction_has-0.3.0.dist-info/RECORD
